botrnot/__init__.py
botrnot/__main__.py
botrnot/__version__.py
botrnot/botrnot.py
botrnot-1.2.5.dist-info/METADATA
botrnot-1.2.5.dist-info/WHEEL
botrnot-1.2.5.dist-info/entry_points.txt
botrnot-1.2.5.dist-info/top_level.txt
botrnot-1.2.5.dist-info/RECORD
