Metadata-Version: 2.1
Name: botrnot
Version: 1.2.5
Summary: Evaluate if a twitter account is a bot or not
Home-page: https://github.com/jamesacampbell/botrnot
Author: James Campbell
Author-email: james@jamescampbell.us
License: GPLv3
Download-URL: https://github.com/jamesacampbell/botrnot/archive/1.2.5.tar.gz
Keywords: bots,data-analysis,twitter,osint-research,osint
Platform: UNKNOWN
Classifier: Programming Language :: Python :: 3 :: Only
Classifier: Operating System :: OS Independent
Requires-Dist: argparse
Requires-Dist: beautifultable
Requires-Dist: requests
Requires-Dist: twitter-scraper
Requires-Dist: beautifulsoup4
